{
  "counts": {
    "real_test": 263,
    "synthetic": 496
  },
  "utility": {
    "TRTR": 0.7262357414448669,
    "TSTR": 0.7300380228136882,
    "gap": 0.0038022813688213253,
    "n_test": 263,
    "n_synth": 496
  },
  "detectability": {
    "accuracy": 0.649402390438247,
    "auc": 0.6714325763947294
  },
  "distribution": {
    "ks": [
      {
        "band": "Delta",
        "ks_stat": 0.1002851711026616,
        "p_value": 0.05782785883749837
      },
      {
        "band": "Theta",
        "ks_stat": 0.08044584815405373,
        "p_value": 0.20181732551447407
      },
      {
        "band": "Alpha",
        "ks_stat": 0.06479210106709186,
        "p_value": 0.4424298276610686
      },
      {
        "band": "Beta",
        "ks_stat": 0.08424812952287501,
        "p_value": 0.16225097777056793
      },
      {
        "band": "Gamma",
        "ks_stat": 0.07764013246657672,
        "p_value": 0.235456679512354
      }
    ],
    "mmd": -1.3013929159968711,
    "corr_sim": 0.9849554425181344,
    "spearman": [
      0.09165255817957971,
      -0.044962783608628556,
      -0.006029296178620536,
      0.07344131314640935,
      -0.00160561344625409
    ]
  }
}